sentimizer.py
sentimizer-2.0.dist-info/LICENSE
sentimizer-2.0.dist-info/METADATA
sentimizer-2.0.dist-info/WHEEL
sentimizer-2.0.dist-info/top_level.txt
sentimizer-2.0.dist-info/RECORD
