Metadata-Version: 2.1
Name: sentimizer
Version: 2.0
Summary: Sentimizer will measure sentiment around specific entities within text.
Home-page: https://github.com/metalcorebear/sentimizer
Author: metalcorebear
Author-email: mark.mbailey@gmail.com
License: UNKNOWN
Platform: UNKNOWN
Classifier: Programming Language :: Python :: 3.9
Classifier: License :: OSI Approved :: MIT License
Classifier: Operating System :: OS Independent
Requires-Python: >=2.7
License-File: LICENSE
Requires-Dist: nltk
Requires-Dist: spacy
Requires-Dist: NRCLex
